lerobot_motor_starai/__init__.py
lerobot_motor_starai/starai.py
lerobot_motor_starai/tables.py
lerobot_motor_starai-0.0.4.dist-info/licenses/LICENSE
lerobot_motor_starai-0.0.4.dist-info/METADATA
lerobot_motor_starai-0.0.4.dist-info/WHEEL
lerobot_motor_starai-0.0.4.dist-info/top_level.txt
lerobot_motor_starai-0.0.4.dist-info/RECORD
