Metadata-Version: 2.4
Name: lerobot_motor_starai
Version: 0.0.4
Summary: LeRobot motor integration
Author: Welt-liu
Author-email: 1994524450@qq.com
Classifier: Programming Language :: Python :: 3
Classifier: License :: OSI Approved :: Apache Software License
Classifier: Operating System :: OS Independent
Requires-Python: >=3.7
License-File: LICENSE
Requires-Dist: lerobot
Requires-Dist: fashionstar-uart-sdk>=1.3.6
Dynamic: author
Dynamic: author-email
Dynamic: classifier
Dynamic: license-file
Dynamic: requires-dist
Dynamic: requires-python
Dynamic: summary
